<sportsData><vers>7</vers><runSummary><workoutName>Basic</workoutName><time>2011-05-09T15:44:26-07:00</time><duration>1345383</duration><durationString>22:25</durationString><distance unit="km">4.6834</distance><distanceString>2.91 mi</distanceString><pace>07:42 min/mi</pace><calories>306</calories><battery></battery><musicChoice>0</musicChoice><stepCounts><walkBegin>3998</walkBegin><walkEnd>4002</walkEnd><runBegin>16356</runBegin><runEnd>20502</runEnd></stepCounts><lifetime><uncalibratedLifetimeWalkMiles>1.968</uncalibratedLifetimeWalkMiles><uncalibratedLifetimeRunMiles>17.507</uncalibratedLifetimeRunMiles><calibratedLifetimeWalkMiles>1.968</calibratedLifetimeWalkMiles><calibratedLifetimeRunMiles>15.222</calibratedLifetimeRunMiles><batteryLifetime>7</batteryLifetime></lifetime></runSummary><template><templateID>8D495DCE</templateID><templateName>Basic</templateName></template><goal type="" unit="" value=""><distance>0.0000</distance><duration>0</duration><calories>0</calories></goal><userInfo><empedID>5C043264VSX</empedID><weight>63.6</weight><device>iPod</device><calibration></calibration></userInfo><ipodInfo><model>iPod</model><softwareVersion>4.2.1</softwareVersion><serialNumber>c53bb97a492d9693dae74e04a89172d48de8986d</serialNumber></ipodInfo><startTime>2011-05-09T15:44:26-07:00</startTime><snapShotList snapShotType="userClick"><snapShot event="onDemandVP"><duration>1138099</duration><distance>3.966</distance><pace>14217816</pace></snapShot><snapShot event="onDemandVP"><duration>1341665</duration><distance>4.677</distance><pace>18361293</pace></snapShot><snapShot event="stop"><duration>1345383</duration><distance>4.683</distance><pace>0</pace></snapShot></snapShotList><snapShotList snapShotType="kmSplit"><snapShot><duration>291000</duration><distance>1.000</distance><pace>14867774</pace></snapShot><snapShot><duration>585000</duration><distance>2.003</distance><pace>19742452</pace></snapShot><snapShot><duration>865000</duration><distance>3.002</distance><pace>19011249</pace></snapShot><snapShot><duration>1146000</duration><distance>4.001</distance><pace>15030263</pace></snapShot></snapShotList><snapShotList snapShotType="mileSplit"><snapShot><duration>469000</duration><distance>1.612</distance><pace>17955070</pace></snapShot><snapShot><duration>926000</duration><distance>3.220</distance><pace>17873826</pace></snapShot></snapShotList><extendedDataList><extendedData dataType="distance" intervalType="time" intervalUnit="s" intervalValue="10">0.0415, 0.0762, 0.1115, 0.1472, 0.1822, 0.2226, 0.2560, 0.2893, 0.3232, 0.3569, 0.3938, 0.4221, 0.4536, 0.4848, 0.5171, 0.5516, 0.5817, 0.6113, 0.6456, 0.6772, 0.7134, 0.7441, 0.7833, 0.8224, 0.8606, 0.9010, 0.9320, 0.9634, 0.9923, 1.0280, 1.0644, 1.0983, 1.1250, 1.1594, 1.1904, 1.2253, 1.2687, 1.3070, 1.3407, 1.3738, 1.4133, 1.4494, 1.4782, 1.5095, 1.5379, 1.5704, 1.6149, 1.6455, 1.6821, 1.7144, 1.7497, 1.7828, 1.8118, 1.8450, 1.8800, 1.9133, 1.9502, 1.9870, 2.0158, 2.0476, 2.0825, 2.1181, 2.1592, 2.1905, 2.2191, 2.2519, 2.2939, 2.3291, 2.3593, 2.3931, 2.4318, 2.4653, 2.5046, 2.5349, 2.5720, 2.6122, 2.6523, 2.6950, 2.7291, 2.7664, 2.8030, 2.8423, 2.8815, 2.9165, 2.9526, 2.9857, 3.0191, 3.0594, 3.0971, 3.1317, 3.1663, 3.1965, 3.2338, 3.2759, 3.3129, 3.3469, 3.3786, 3.4130, 3.4455, 3.4792, 3.5113, 3.5453, 3.5787, 3.6257, 3.6622, 3.7013, 3.7407, 3.7760, 3.8070, 3.8350, 3.8685, 3.9020, 3.9314, 3.9751, 4.0135, 4.0440, 4.0789, 4.1061, 4.1481, 4.1850, 4.2230, 4.2644, 4.3062, 4.3437, 4.3828, 4.4148, 4.4508, 4.4836, 4.5234, 4.5563, 4.5851, 4.6140, 4.6461, 4.6736</extendedData></extendedDataList></sportsData>
